chromologger/__init__.py
chromologger/main.py
chromologger/utils/__init__.py
chromologger/utils/dates.py
chromologger/utils/files_manager.py
chromologger-0.1.9.post2.dist-info/licenses/LICENSE
chromologger-0.1.9.post2.dist-info/METADATA
chromologger-0.1.9.post2.dist-info/WHEEL
chromologger-0.1.9.post2.dist-info/top_level.txt
chromologger-0.1.9.post2.dist-info/RECORD
