Metadata-Version: 2.4
Name: chromologger
Version: 0.1.9.post2
Summary: Chromologger está diseñado para facilitar la creación de registros (logs) en aplicaciones desarrolladas con Python
Author-email: dev2forge <support@dev2forge.software>
Maintainer-email: tutosrive <tutosrive@dev2forge.software>
License-Expression: MIT
Project-URL: Homepage, https://docs.dev2forge.software/chromologger/
Project-URL: Repository, https://github.com/Dev2Forge/chromologger/
Project-URL: YouTube, https://www.youtube.com/@dev2forge
Project-URL: Issues, https://github.com/Dev2Forge/chromologger/issues/
Project-URL: Changelog, https://github.com/Dev2Forge/chromologger/blob/main/CHANGELOG.md
Keywords: logs,dev2forge,logging,log,logger,exception logging,error logging,python logs,file logger,structured logs,debugging,monitoring,chromologger,simple logger,python utility,console logger,developer tool,log formatter,log file
Classifier: Development Status :: 5 - Production/Stable
Classifier: Intended Audience :: Developers
Classifier: Intended Audience :: Information Technology
Classifier: Intended Audience :: System Administrators
Classifier: Topic :: Software Development :: Libraries
Classifier: Topic :: Software Development :: Debuggers
Classifier: Topic :: System :: Monitoring
Classifier: Topic :: System :: Logging
Classifier: Topic :: Utilities
Classifier: Programming Language :: Python
Classifier: Programming Language :: Python :: 3.8
Classifier: Programming Language :: Python :: 3.10
Classifier: Programming Language :: Python :: 3.11
Classifier: Programming Language :: Python :: 3.12
Classifier: Programming Language :: Python :: 3.13
Classifier: Programming Language :: Python :: 3.14
Classifier: Operating System :: OS Independent
Classifier: Environment :: Console
Classifier: Environment :: Other Environment
Requires-Python: >=3.8
License-File: LICENSE
Requires-Dist: chromolog==0.2.5
Dynamic: license-file
